magnus_extension_kubeflow/implementation.py
magnus_extension_kubeflow/integration.py
magnus_extension_kubeflow-0.1.0.dist-info/WHEEL
magnus_extension_kubeflow-0.1.0.dist-info/entry_points.txt
magnus_extension_kubeflow-0.1.0.dist-info/METADATA
magnus_extension_kubeflow-0.1.0.dist-info/RECORD
