Metadata-Version: 2.1
Name: magnus-extension-kubeflow
Version: 0.1.0
Summary: Kubeflow executor
Home-page: https://github.com/AstraZeneca/magnus-extensions/
License: Apache-2.0
Author: Vijay Vammi
Author-email: mesanthu@gmail.com
Requires-Python: >=3.8,<4.0
Classifier: License :: OSI Approved :: Apache Software License
Classifier: Programming Language :: Python :: 3
Classifier: Programming Language :: Python :: 3.8
Classifier: Programming Language :: Python :: 3.9
Classifier: Programming Language :: Python :: 3.10
Classifier: Programming Language :: Python :: 3.11
Requires-Dist: kfp (>=1.8.18,<2.0.0)
Requires-Dist: magnus (>=0.4.1,<0.5.0)
Project-URL: Documentation, https://astrazeneca.github.io/magnus-extensions/
Project-URL: Repository, https://github.com/AstraZeneca/magnus-extensions/
